LICENSE
MANIFEST.in
README.rst
setup.py
show_my_designs/__init__.py
show_my_designs/gui.py
show_my_designs/icon.png
show_my_designs.egg-info/PKG-INFO
show_my_designs.egg-info/SOURCES.txt
show_my_designs.egg-info/dependency_links.txt
show_my_designs.egg-info/entry_points.txt
show_my_designs.egg-info/requires.txt
show_my_designs.egg-info/top_level.txt