Metadata-Version: 1.0
Name: show-my-designs
Version: 1.2.1
Summary:  A GUI for visualizing and interacting with score vs RMSD plots.
Home-page: https://github.com/Kortemme-Lab/show_my_designs
Author: Kale Kundert
Author-email: kale.kundert@ucsf.edu
License: GPLv3
Platform: UNKNOWN
